ALU/src/half_adder.vhdl
library ieee;
use ieee.std_logic_1164.all;

entity half_adder is
    port (
        a, b : in std_logic_vector (31 downto 0);
        s, c : out std_logic_vector (31 downto 0)
    );
end half_adder;

architecture habhv of half_adder is

begin
    s <= a xor b;
    c <= a and b;
end habhv;

ALU/src/full_adder.vhdl
library ieee;
use ieee.numeric_std.all;

entity full_adder is
    port (
        a, b, ci : in signed (31 downto 0);
        s, c : out signed (31 downto 0)
    );
end full_adder;


architecture fadbhv of full_adder is
    component half_adder
        port (
            a, b : in signed (31 downto 0);
            s, c : out signed (31 downto 0)
        );
    end component;

    for half_adder_0: half_adder use entity work.half_adder;
    for half_adder_1: half_adder use entity work.half_adder;
    signal asb, aab, asbco: signed (31 downto 0);

    -- Instantiation
begin
    half_adder_0: half_adder port map(
        -- entity-signal-name => local-signal-name
        a => a,
        b => b,
        s => asb,
        c => aab
    );
    half_adder_1: half_adder port map(
        a => asb,
        b => ci,
        s => s,
        c => asbco
    );

    c <= aab or asbco;
end fadbhv;

ALU/src/full_adder_tb.vhdl
library ieee;
use ieee.std_logic_1164.all;
use ieee.numeric_std.all;

--  A testbench has no ports.
entity full_adder_tb is
end full_adder_tb;

architecture behav of full_adder_tb is
    --  Declaration of the component that will be instantiated.
    function to_string ( a: signed) return string is
    variable b : string (1 to a'length) := (others => NUL);
    variable stri : integer := 1;
    begin
        for i in a'range loop
            b(stri) := std_logic'image(a((i)))(2);
        stri := stri+1;
        end loop;
    return b;
    end function;

    component full_adder
        port (
            a, b, ci : in signed (31 downto 0);
            s, c : out signed (31 downto 0)
        );
    end component;

    --  Specifies which entity is bound with the component.
    for full_adder_0: full_adder use entity work.full_adder;
    signal a, b, ci, s, c : signed (31 downto 0);

begin
    --  Component instantiation.
    full_adder_0: full_adder port map (a => a, b => b, ci => ci, s => s, c => c);

--  This process does the real job.
process
    type pattern_type is record
        --  The inputs of the full_adder.
        a, b, ci : signed (31 downto 0);
        --  The expected outputs of the full_adder.
        s, c : signed (31 downto 0);
    end record;

--  The patterns to apply.
    type pattern_array is array (natural range <>) of pattern_type;
    constant patterns : pattern_array :=
        (
            (
                "00000000000000000000000000000001",
                "00000000000000000000000000000001",
                "00000000000000000000000000000000",
                "00000000000000000000000000000000",
                "00000000000000000000000000000001"
            ),
            (
                "00000100001110011000100011110101",
                "00000100001110011000100110100110",
                "00000000000000000000000000000000",
                "00000000000000000000000101010011",
                "00000100001110011000100010100100"
            ),
            (
                "01000100001110011010100011110101",
                "00111100001010111000000010100110",
                "00110111101111000010101001010010",
                "01001111101011100000001000000001",
                "00110100001110011010100011110110"
            ),
            (
                "11011100110111111011011011110100",
                "11100110111001101110101011011101",
                "10011110001001001010010111101110",
                "10100100000111011111100111000111",
                "11011110111001101010011011111100"
            ),
            (
                "01101000011010011100000011001000",
                "10010101010110100000010010000111",
                "11100011010000100000110000001101",
                "00011110011100011100100001000010",
                "11100001010010100000010010001101"
            ),
            (
                "00011010001011001100010110100111",
                "11101001011100010110010000101110",
                "01000100011101100111101011010110",
                "10110111001010111101101101011111",
                "01001000011101000110010010100110"
            ),
            (
                "11001010001100111000011100000010",
                "11110000101111010011111010011010",
                "11000101000011010010000000001000",
                "11111111100000111001100110010000",
                "11000000001111010010011000001010"
            ),
            (
                "00100110100011100101100100000111",
                "10101010110110011000011111001110",
                "01000010010101111111111111001101",
                "11001110000000000010000100000100",
                "00100010110111111101111111001111"
            ),
            (
                "11011101101111101100010110101111",
                "01001001111011001110110011010001",
                "10000100010011100101100111100110",
                "00010000000111000111000010011000",
                "11001101111011101100110111100111"
            ),
            (
                "11110001001000010001101001111100",
                "10001101000010100010100101100101",
                "10110111100010100001110111000110",
                "11001011101000010010111011011111",
                "10110101000010100001100101100100"
            ),
            (
                "11101011111010000110010010101011",
                "10101110010010000101110110011111",
                "00100110010111011110011100000010",
                "01100011111111011101111000110110",
                "10101110010010000110010110001011"
            ),
            (
                "01010010110000001100001111010111",
                "10010011100101111010001001110000",
                "00111011100111010001000010000111",
                "11111010110010100111000100100000",
                "00010011100101011000001011010111"
            ),
            (
                "10100100000111100110111100100100",
                "11101000100010100001101100111101",
                "01000100100111001011111100000011",
                "00001000000010001100101100011010",
                "11100100100111100011111100100101"
            ),
            (
                "10111111011011011001110001011011",
                "01000010111000000100111001010000",
                "11001000011000001100111000100011",
                "00110101111011010001110000101000",
                "11001010011000001100111001010011"
            ),
            (
                "01010000011011010100100110000100",
                "01110101110010001101100010000001",
                "11000111111111100111011111011001",
                "11100010010110111110011011011100",
                "01010101111011000101100110000001"
            ),
            (
                "00011010000101011110110110110100",
                "00000011000001100101010110010001",
                "00000011000011111001011100001101",
                "00011010000111000010111100101000",
                "00000011000001111101010110010101"
            ),
            (
                "01110101110101101101100011101001",
                "11001001001110110111111001101111",
                "00111000011100110100001001001101",
                "10000100100111101110010011001011",
                "01111001011100110101101001101101"
            ),
            (
                "01110001000101000101011000101001",
                "10101101000100010101111110100011",
                "01001111011001110000000011111100",
                "10010011011000100000100101110110",
                "01101101000101010101011010101001"
            ),
            (
                "01010101000001111011000110011100",
                "00010110110001000110010000001000",
                "01100101110101001000110010001000",
                "00100110000101110101100100011100",
                "01010101110001001010010010001000"
            ),
            (
                "10101100010010011001011101111011",
                "00101100111110100000000100001010",
                "00010000010100001000001000110100",
                "10010000111000110001010001000101",
                "00101100010110001000001100111010"
            ),
            (
                "01001010001111101011100001000010",
                "01100001001100100100100010111011",
                "10001011101100000001011111011001",
                "10100000101111001110011100100000",
                "01001011001100100001100011011011"
            ),
            (
                "10110101010100010110111010100010",
                "11100110101100111100110101001000",
                "10110111101110111101001110011111",
                "11100100010110010111000001110101",
                "10110111101100111100111110001010"
            ),
            (
                "01101001010101000100010110001100",
                "11010100010110110110100110111001",
                "10100101101010001011110000100000",
                "00011000101001111001000000010101",
                "11100101010110000110110110101000"
            ),
            (
                "11110101101111000110111010100101",
                "10111100010100100010111100101101",
                "11000011001001011101101111000100",
                "10001010110010111001101001001100",
                "11110101001101000110111110100101"
            ),
            (
                "01010101111110101010100011011100",
                "11110100111000010001010001100000",
                "01100111111111100111110010010010",
                "11000110111001011100000000101110",
                "01110101111110100011110011010000"
            )
        );

begin
    --  Check each pattern.
    for i in patterns'range loop
    --  Set the inputs.
    a <= patterns(i).a;
    b <= patterns(i).b;
    ci <= patterns(i).ci;
    --  Wait for the results.
    wait for 1 ns;
        --  Check the outputs.
            assert s = patterns(i).s
                report LF &
                "a : " & to_string(a) & LF &
                "b : " & to_string(b) & LF &
                "ci : " & to_string(ci) & LF &
                "s : " & to_string(s) & LF &
                "c : " & to_string(c) & LF &
                "Bad sum value";
            assert c = patterns(i).c
                report LF &
                "a : " & to_string(a) & LF &
                "b : " & to_string(b) & LF &
                "ci : " & to_string(ci) & LF &
                "s : " & to_string(s) & LF &
                "c : " & to_string(c) & LF &
                "Bad carry out value";
        end loop;
            assert false report "end of test" severity note;
        wait;
    end process;
end behav;

ALU/src/full_adder_tb.vcd
$date
  Fri May  5 19:12:52 2023
$end
$version
  GHDL v0
$end
$timescale
  1 fs
$end
$scope module standard $end
$upscope $end
$scope module std_logic_1164 $end
$upscope $end
$scope module full_adder_tb $end
$var reg 32 ! a[31:0] $end
$var reg 32 " b[31:0] $end
$var reg 32 # ci[31:0] $end
$var reg 32 $ s[31:0] $end
$var reg 32 % c[31:0] $end
$scope module full_adder_0 $end
$var reg 32 & a[31:0] $end
$var reg 32 ' b[31:0] $end
$var reg 32 ( ci[31:0] $end
$var reg 32 ) s[31:0] $end
$var reg 32 * c[31:0] $end
$var reg 32 + asb[31:0] $end
$var reg 32 , aab[31:0] $end
$var reg 32 - asbco[31:0] $end
$scope module half_adder_0 $end
$var reg 32 . a[31:0] $end
$var reg 32 / b[31:0] $end
$var reg 32 0 s[31:0] $end
$var reg 32 1 c[31:0] $end
$upscope $end
$scope module half_adder_1 $end
$var reg 32 2 a[31:0] $end
$var reg 32 3 b[31:0] $end
$var reg 32 4 s[31:0] $end
$var reg 32 5 c[31:0] $end
$upscope $end
$upscope $end
$upscope $end
$enddefinitions $end
#0
b00000000000000000000000000000001 !
b00000000000000000000000000000001 "
b00000000000000000000000000000000 #
b00000000000000000000000000000000 $
b00000000000000000000000000000001 %
b00000000000000000000000000000001 &
b00000000000000000000000000000001 '
b00000000000000000000000000000000 (
b00000000000000000000000000000000 )
b00000000000000000000000000000001 *
b00000000000000000000000000000000 +
b00000000000000000000000000000001 ,
b00000000000000000000000000000000 -
b00000000000000000000000000000001 .
b00000000000000000000000000000001 /
b00000000000000000000000000000000 0
b00000000000000000000000000000001 1
b00000000000000000000000000000000 2
b00000000000000000000000000000000 3
b00000000000000000000000000000000 4
b00000000000000000000000000000000 5
#1000000
b00000100001110011000100011110101 !
b00000100001110011000100110100110 "
b00000000000000000000000101010011 $
b00000100001110011000100010100100 %
b00000100001110011000100011110101 &
b00000100001110011000100110100110 '
b00000000000000000000000101010011 )
b00000100001110011000100010100100 *
b00000000000000000000000101010011 +
b00000100001110011000100010100100 ,
b00000100001110011000100011110101 .
b00000100001110011000100110100110 /
b00000000000000000000000101010011 0
b00000100001110011000100010100100 1
b00000000000000000000000101010011 2
b00000000000000000000000101010011 4
#2000000
b01000100001110011010100011110101 !
b00111100001010111000000010100110 "
b00110111101111000010101001010010 #
b01001111101011100000001000000001 $
b00110100001110011010100011110110 %
b01000100001110011010100011110101 &
b00111100001010111000000010100110 '
b00110111101111000010101001010010 (
b01001111101011100000001000000001 )
b00110100001110011010100011110110 *
b01111000000100100010100001010011 +
b00000100001010011000000010100100 ,
b00110000000100000010100001010010 -
b01000100001110011010100011110101 .
b00111100001010111000000010100110 /
b01111000000100100010100001010011 0
b00000100001010011000000010100100 1
b01111000000100100010100001010011 2
b00110111101111000010101001010010 3
b01001111101011100000001000000001 4
b00110000000100000010100001010010 5
#3000000
b11011100110111111011011011110100 !
b11100110111001101110101011011101 "
b10011110001001001010010111101110 #
b10100100000111011111100111000111 $
b11011110111001101010011011111100 %
b11011100110111111011011011110100 &
b11100110111001101110101011011101 '
b10011110001001001010010111101110 (
b10100100000111011111100111000111 )
b11011110111001101010011011111100 *
b00111010001110010101110000101001 +
b11000100110001101010001011010100 ,
b00011010001000000000010000101000 -
b11011100110111111011011011110100 .
b11100110111001101110101011011101 /
b00111010001110010101110000101001 0
b11000100110001101010001011010100 1
b00111010001110010101110000101001 2
b10011110001001001010010111101110 3
b10100100000111011111100111000111 4
b00011010001000000000010000101000 5
#4000000
b01101000011010011100000011001000 !
b10010101010110100000010010000111 "
b11100011010000100000110000001101 #
b00011110011100011100100001000010 $
b11100001010010100000010010001101 %
b01101000011010011100000011001000 &
b10010101010110100000010010000111 '
b11100011010000100000110000001101 (
b00011110011100011100100001000010 )
b11100001010010100000010010001101 *
b11111101001100111100010001001111 +
b00000000010010000000000010000000 ,
b11100001000000100000010000001101 -
b01101000011010011100000011001000 .
b10010101010110100000010010000111 /
b11111101001100111100010001001111 0
b00000000010010000000000010000000 1
b11111101001100111100010001001111 2
b11100011010000100000110000001101 3
b00011110011100011100100001000010 4
b11100001000000100000010000001101 5
#5000000
b00011010001011001100010110100111 !
b11101001011100010110010000101110 "
b01000100011101100111101011010110 #
b10110111001010111101101101011111 $
b01001000011101000110010010100110 %
b00011010001011001100010110100111 &
b11101001011100010110010000101110 '
b01000100011101100111101011010110 (
b10110111001010111101101101011111 )
b01001000011101000110010010100110 *
b11110011010111011010000110001001 +
b00001000001000000100010000100110 ,
b01000000010101000010000010000000 -
b00011010001011001100010110100111 .
b11101001011100010110010000101110 /
b11110011010111011010000110001001 0
b00001000001000000100010000100110 1
b11110011010111011010000110001001 2
b01000100011101100111101011010110 3
b10110111001010111101101101011111 4
b01000000010101000010000010000000 5
#6000000
b11001010001100111000011100000010 !
b11110000101111010011111010011010 "
b11000101000011010010000000001000 #
b11111111100000111001100110010000 $
b11000000001111010010011000001010 %
b11001010001100111000011100000010 &
b11110000101111010011111010011010 '
b11000101000011010010000000001000 (
b11111111100000111001100110010000 )
b11000000001111010010011000001010 *
b00111010100011101011100110011000 +
b11000000001100010000011000000010 ,
b00000000000011000010000000001000 -
b11001010001100111000011100000010 .
b11110000101111010011111010011010 /
b00111010100011101011100110011000 0
b11000000001100010000011000000010 1
b00111010100011101011100110011000 2
b11000101000011010010000000001000 3
b11111111100000111001100110010000 4
b00000000000011000010000000001000 5
#7000000
b00100110100011100101100100000111 !
b10101010110110011000011111001110 "
b01000010010101111111111111001101 #
b11001110000000000010000100000100 $
b00100010110111111101111111001111 %
b00100110100011100101100100000111 &
b10101010110110011000011111001110 '
b01000010010101111111111111001101 (
b11001110000000000010000100000100 )
b00100010110111111101111111001111 *
b10001100010101111101111011001001 +
b00100010100010000000000100000110 ,
b00000000010101111101111011001001 -
b00100110100011100101100100000111 .
b10101010110110011000011111001110 /
b10001100010101111101111011001001 0
b00100010100010000000000100000110 1
b10001100010101111101111011001001 2
b01000010010101111111111111001101 3
b11001110000000000010000100000100 4
b00000000010101111101111011001001 5
#8000000
b11011101101111101100010110101111 !
b01001001111011001110110011010001 "
b10000100010011100101100111100110 #
b00010000000111000111000010011000 $
b11001101111011101100110111100111 %
b11011101101111101100010110101111 &
b01001001111011001110110011010001 '
b10000100010011100101100111100110 (
b00010000000111000111000010011000 )
b11001101111011101100110111100111 *
b10010100010100100010100101111110 +
b01001001101011001100010010000001 ,
b10000100010000100000100101100110 -
b11011101101111101100010110101111 .
b01001001111011001110110011010001 /
b10010100010100100010100101111110 0
b01001001101011001100010010000001 1
b10010100010100100010100101111110 2
b10000100010011100101100111100110 3
b00010000000111000111000010011000 4
b10000100010000100000100101100110 5
#9000000
b11110001001000010001101001111100 !
b10001101000010100010100101100101 "
b10110111100010100001110111000110 #
b11001011101000010010111011011111 $
b10110101000010100001100101100100 %
b11110001001000010001101001111100 &
b10001101000010100010100101100101 '
b10110111100010100001110111000110 (
b11001011101000010010111011011111 )
b10110101000010100001100101100100 *
b01111100001010110011001100011001 +
b10000001000000000000100001100100 ,
b00110100000010100001000100000000 -
b11110001001000010001101001111100 .
b10001101000010100010100101100101 /
b01111100001010110011001100011001 0
b10000001000000000000100001100100 1
b01111100001010110011001100011001 2
b10110111100010100001110111000110 3
b11001011101000010010111011011111 4
b00110100000010100001000100000000 5
#10000000
b11101011111010000110010010101011 !
b10101110010010000101110110011111 "
b00100110010111011110011100000010 #
b01100011111111011101111000110110 $
b10101110010010000110010110001011 %
b11101011111010000110010010101011 &
b10101110010010000101110110011111 '
b00100110010111011110011100000010 (
b01100011111111011101111000110110 )
b10101110010010000110010110001011 *
b01000101101000000011100100110100 +
b10101010010010000100010010001011 ,
b00000100000000000010000100000000 -
b11101011111010000110010010101011 .
b10101110010010000101110110011111 /
b01000101101000000011100100110100 0
b10101010010010000100010010001011 1
b01000101101000000011100100110100 2
b00100110010111011110011100000010 3
b01100011111111011101111000110110 4
b00000100000000000010000100000000 5
#11000000
b01010010110000001100001111010111 !
b10010011100101111010001001110000 "
b00111011100111010001000010000111 #
b11111010110010100111000100100000 $
b00010011100101011000001011010111 %
b01010010110000001100001111010111 &
b10010011100101111010001001110000 '
b00111011100111010001000010000111 (
b11111010110010100111000100100000 )
b00010011100101011000001011010111 *
b11000001010101110110000110100111 +
b00010010100000001000001001010000 ,
b00000001000101010000000010000111 -
b01010010110000001100001111010111 .
b10010011100101111010001001110000 /
b11000001010101110110000110100111 0
b00010010100000001000001001010000 1
b11000001010101110110000110100111 2
b00111011100111010001000010000111 3
b11111010110010100111000100100000 4
b00000001000101010000000010000111 5
#12000000
b10100100000111100110111100100100 !
b11101000100010100001101100111101 "
b01000100100111001011111100000011 #
b00001000000010001100101100011010 $
b11100100100111100011111100100101 %
b10100100000111100110111100100100 &
b11101000100010100001101100111101 '
b01000100100111001011111100000011 (
b00001000000010001100101100011010 )
b11100100100111100011111100100101 *
b01001100100101000111010000011001 +
b10100000000010100000101100100100 ,
b01000100100101000011010000000001 -
b10100100000111100110111100100100 .
b11101000100010100001101100111101 /
b01001100100101000111010000011001 0
b10100000000010100000101100100100 1
b01001100100101000111010000011001 2
b01000100100111001011111100000011 3
b00001000000010001100101100011010 4
b01000100100101000011010000000001 5
#13000000
b10111111011011011001110001011011 !
b01000010111000000100111001010000 "
b11001000011000001100111000100011 #
b00110101111011010001110000101000 $
b11001010011000001100111001010011 %
b10111111011011011001110001011011 &
b01000010111000000100111001010000 '
b11001000011000001100111000100011 (
b00110101111011010001110000101000 )
b11001010011000001100111001010011 *
b11111101100011011101001000001011 +
b00000010011000000000110001010000 ,
b11001000000000001100001000000011 -
b10111111011011011001110001011011 .
b01000010111000000100111001010000 /
b11111101100011011101001000001011 0
b00000010011000000000110001010000 1
b11111101100011011101001000001011 2
b11001000011000001100111000100011 3
b00110101111011010001110000101000 4
b11001000000000001100001000000011 5
#14000000
b01010000011011010100100110000100 !
b01110101110010001101100010000001 "
b11000111111111100111011111011001 #
b11100010010110111110011011011100 $
b01010101111011000101100110000001 %
b01010000011011010100100110000100 &
b01110101110010001101100010000001 '
b11000111111111100111011111011001 (
b11100010010110111110011011011100 )
b01010101111011000101100110000001 *
b00100101101001011001000100000101 +
b01010000010010000100100010000000 ,
b00000101101001000001000100000001 -
b01010000011011010100100110000100 .
b01110101110010001101100010000001 /
b00100101101001011001000100000101 0
b01010000010010000100100010000000 1
b00100101101001011001000100000101 2
b11000111111111100111011111011001 3
b11100010010110111110011011011100 4
b00000101101001000001000100000001 5
#15000000
b00011010000101011110110110110100 !
b00000011000001100101010110010001 "
b00000011000011111001011100001101 #
b00011010000111000010111100101000 $
b00000011000001111101010110010101 %
b00011010000101011110110110110100 &
b00000011000001100101010110010001 '
b00000011000011111001011100001101 (
b00011010000111000010111100101000 )
b00000011000001111101010110010101 *
b00011001000100111011100000100101 +
b00000010000001000100010110010000 ,
b00000001000000111001000000000101 -
b00011010000101011110110110110100 .
b00000011000001100101010110010001 /
b00011001000100111011100000100101 0
b00000010000001000100010110010000 1
b00011001000100111011100000100101 2
b00000011000011111001011100001101 3
b00011010000111000010111100101000 4
b00000001000000111001000000000101 5
#16000000
b01110101110101101101100011101001 !
b11001001001110110111111001101111 "
b00111000011100110100001001001101 #
b10000100100111101110010011001011 $
b01111001011100110101101001101101 %
b01110101110101101101100011101001 &
b11001001001110110111111001101111 '
b00111000011100110100001001001101 (
b10000100100111101110010011001011 )
b01111001011100110101101001101101 *
b10111100111011011010011010000110 +
b01000001000100100101100001101001 ,
b00111000011000010000001000000100 -
b01110101110101101101100011101001 .
b11001001001110110111111001101111 /
b10111100111011011010011010000110 0
b01000001000100100101100001101001 1
b10111100111011011010011010000110 2
b00111000011100110100001001001101 3
b10000100100111101110010011001011 4
b00111000011000010000001000000100 5
#17000000
b01110001000101000101011000101001 !
b10101101000100010101111110100011 "
b01001111011001110000000011111100 #
b10010011011000100000100101110110 $
b01101101000101010101011010101001 %
b01110001000101000101011000101001 &
b10101101000100010101111110100011 '
b01001111011001110000000011111100 (
b10010011011000100000100101110110 )
b01101101000101010101011010101001 *
b11011100000001010000100110001010 +
b00100001000100000101011000100001 ,
b01001100000001010000000010001000 -
b01110001000101000101011000101001 .
b10101101000100010101111110100011 /
b11011100000001010000100110001010 0
b00100001000100000101011000100001 1
b11011100000001010000100110001010 2
b01001111011001110000000011111100 3
b10010011011000100000100101110110 4
b01001100000001010000000010001000 5
#18000000
b01010101000001111011000110011100 !
b00010110110001000110010000001000 "
b01100101110101001000110010001000 #
b00100110000101110101100100011100 $
b01010101110001001010010010001000 %
b01010101000001111011000110011100 &
b00010110110001000110010000001000 '
b01100101110101001000110010001000 (
b00100110000101110101100100011100 )
b01010101110001001010010010001000 *
b01000011110000111101010110010100 +
b00010100000001000010000000001000 ,
b01000001110000001000010010000000 -
b01010101000001111011000110011100 .
b00010110110001000110010000001000 /
b01000011110000111101010110010100 0
b00010100000001000010000000001000 1
b01000011110000111101010110010100 2
b01100101110101001000110010001000 3
b00100110000101110101100100011100 4
b01000001110000001000010010000000 5
#19000000
b10101100010010011001011101111011 !
b00101100111110100000000100001010 "
b00010000010100001000001000110100 #
b10010000111000110001010001000101 $
b00101100010110001000001100111010 %
b10101100010010011001011101111011 &
b00101100111110100000000100001010 '
b00010000010100001000001000110100 (
b10010000111000110001010001000101 )
b00101100010110001000001100111010 *
b10000000101100111001011001110001 +
b00101100010010000000000100001010 ,
b00000000000100001000001000110000 -
b10101100010010011001011101111011 .
b00101100111110100000000100001010 /
b10000000101100111001011001110001 0
b00101100010010000000000100001010 1
b10000000101100111001011001110001 2
b00010000010100001000001000110100 3
b10010000111000110001010001000101 4
b00000000000100001000001000110000 5
#20000000
b01001010001111101011100001000010 !
b01100001001100100100100010111011 "
b10001011101100000001011111011001 #
b10100000101111001110011100100000 $
b01001011001100100001100011011011 %
b01001010001111101011100001000010 &
b01100001001100100100100010111011 '
b10001011101100000001011111011001 (
b10100000101111001110011100100000 )
b01001011001100100001100011011011 *
b00101011000011001111000011111001 +
b01000000001100100000100000000010 ,
b00001011000000000001000011011001 -
b01001010001111101011100001000010 .
b01100001001100100100100010111011 /
b00101011000011001111000011111001 0
b01000000001100100000100000000010 1
b00101011000011001111000011111001 2
b10001011101100000001011111011001 3
b10100000101111001110011100100000 4
b00001011000000000001000011011001 5
#21000000
b10110101010100010110111010100010 !
b11100110101100111100110101001000 "
b10110111101110111101001110011111 #
b11100100010110010111000001110101 $
b10110111101100111100111110001010 %
b10110101010100010110111010100010 &
b11100110101100111100110101001000 '
b10110111101110111101001110011111 (
b11100100010110010111000001110101 )
b10110111101100111100111110001010 *
b01010011111000101010001111101010 +
b10100100000100010100110000000000 ,
b00010011101000101000001110001010 -
b10110101010100010110111010100010 .
b11100110101100111100110101001000 /
b01010011111000101010001111101010 0
b10100100000100010100110000000000 1
b01010011111000101010001111101010 2
b10110111101110111101001110011111 3
b11100100010110010111000001110101 4
b00010011101000101000001110001010 5
#22000000
b01101001010101000100010110001100 !
b11010100010110110110100110111001 "
b10100101101010001011110000100000 #
b00011000101001111001000000010101 $
b11100101010110000110110110101000 %
b01101001010101000100010110001100 &
b11010100010110110110100110111001 '
b10100101101010001011110000100000 (
b00011000101001111001000000010101 )
b11100101010110000110110110101000 *
b10111101000011110010110000110101 +
b01000000010100000100000110001000 ,
b10100101000010000010110000100000 -
b01101001010101000100010110001100 .
b11010100010110110110100110111001 /
b10111101000011110010110000110101 0
b01000000010100000100000110001000 1
b10111101000011110010110000110101 2
b10100101101010001011110000100000 3
b00011000101001111001000000010101 4
b10100101000010000010110000100000 5
#23000000
b11110101101111000110111010100101 !
b10111100010100100010111100101101 "
b11000011001001011101101111000100 #
b10001010110010111001101001001100 $
b11110101001101000110111110100101 %
b11110101101111000110111010100101 &
b10111100010100100010111100101101 '
b11000011001001011101101111000100 (
b10001010110010111001101001001100 )
b11110101001101000110111110100101 *
b01001001111011100100000110001000 +
b10110100000100000010111000100101 ,
b01000001001001000100000110000000 -
b11110101101111000110111010100101 .
b10111100010100100010111100101101 /
b01001001111011100100000110001000 0
b10110100000100000010111000100101 1
b01001001111011100100000110001000 2
b11000011001001011101101111000100 3
b10001010110010111001101001001100 4
b01000001001001000100000110000000 5
#24000000
b01010101111110101010100011011100 !
b11110100111000010001010001100000 "
b01100111111111100111110010010010 #
b11000110111001011100000000101110 $
b01110101111110100011110011010000 %
b01010101111110101010100011011100 &
b11110100111000010001010001100000 '
b01100111111111100111110010010010 (
b11000110111001011100000000101110 )
b01110101111110100011110011010000 *
b10100001000110111011110010111100 +
b01010100111000000000000001000000 ,
b00100001000110100011110010010000 -
b01010101111110101010100011011100 .
b11110100111000010001010001100000 /
b10100001000110111011110010111100 0
b01010100111000000000000001000000 1
b10100001000110111011110010111100 2
b01100111111111100111110010010010 3
b11000110111001011100000000101110 4
b00100001000110100011110010010000 5
